{
    "match_id": "M14",
    "simulation_env": {
        "timestamp": "2026-06-14T22:59:50.480359Z",
        "model": "mistralai/mistral-small-3.1-24b-instruct",
        "hyperparameters": {
            "temperature": 0.0,
            "top_p": 1.0,
            "max_tokens": 2000
        }
    },
    "match_context": {
        "tournament": "FIFA World Cup 2026",
        "phase": "group",
        "team_a": "Belgium",
        "team_b": "Egypt",
        "host_country": "United States"
    },
    "prediction": {
        "confidence": 0.85,
        "knockout_resolution": {
            "ended_in_extra_time": false,
            "ended_in_penalties": false,
            "penalty_shootout_score": null
        },
        "predicted_score": "2-0",
        "predicted_winner": "Belgium",
        "probabilities": {
            "draw": 0.2,
            "team_a_win": 0.65,
            "team_b_win": 0.15
        }
    },
    "post_processing": {
        "performed": false,
        "operations": []
    }
}